blender_basico/__init__.py
blender_basico/apps.py
blender_basico/sasscompiler.py
blender_basico/static/blender_basico/fonts/font-borg-webfont.eot
blender_basico/static/blender_basico/fonts/font-borg-webfont.svg
blender_basico/static/blender_basico/fonts/font-borg-webfont.ttf
blender_basico/static/blender_basico/fonts/font-borg-webfont.woff
blender_basico/static/blender_basico/fonts/roboto-300.woff
blender_basico/static/blender_basico/fonts/roboto-300.woff2
blender_basico/static/blender_basico/fonts/roboto-400.woff
blender_basico/static/blender_basico/fonts/roboto-400.woff2
blender_basico/static/blender_basico/fonts/roboto-700.woff
blender_basico/static/blender_basico/fonts/roboto-700.woff2
blender_basico/static/blender_basico/images/background_gradient_strip_bottom.png
blender_basico/static/blender_basico/images/background_gradient_strip_top.png
blender_basico/static/blender_basico/images/blender_made_by_you.jpg
blender_basico/static/blender_basico/images/favicon.ico
blender_basico/static/blender_basico/images/logo_blender.png
blender_basico/static/blender_basico/images/placeholder_background_small.jpg
blender_basico/static/blender_basico/scripts/tutti/10_navbar.js
blender_basico/static/blender_basico/scripts/tutti/xhr_csfr_token.js
blender_basico/static/blender_basico/scripts/tutti/xhr_errors_parser.js
blender_basico/static/blender_basico/scripts/vendor/bootstrap-4.3.1.min.js
blender_basico/static/blender_basico/scripts/vendor/jquery-3.4.0.min.js
blender_basico/static/blender_basico/scripts/vendor/js.cookie-2.2.0.min.js
blender_basico/static/blender_basico/scripts/vendor/popper-1.15.0.min.js
blender_basico/static/blender_basico/styles/_base.sass
blender_basico/static/blender_basico/styles/_bootstrap_overrides.sass
blender_basico/static/blender_basico/styles/_box.sass
blender_basico/static/blender_basico/styles/_button.sass
blender_basico/static/blender_basico/styles/_cards.sass
blender_basico/static/blender_basico/styles/_code.sass
blender_basico-0.2.2.dist-info/entry_points.txt
blender_basico-0.2.2.dist-info/WHEEL
blender_basico-0.2.2.dist-info/METADATA
blender_basico-0.2.2.dist-info/RECORD
