Metadata-Version: 2.1
Name: blender-basico
Version: 0.2.2
Summary: Django shared app, featuring essential components for blender.org sites.
Author: Francesco Siddi
Author-email: francesco@blender.org
Requires-Python: >=3.6,<4.0
Classifier: Programming Language :: Python :: 3
Classifier: Programming Language :: Python :: 3.10
Classifier: Programming Language :: Python :: 3.6
Classifier: Programming Language :: Python :: 3.7
Classifier: Programming Language :: Python :: 3.8
Classifier: Programming Language :: Python :: 3.9
Requires-Dist: django (>=2.1,<3.0)
Requires-Dist: django-pipeline (>=2,<3)
Requires-Dist: jsmin (>=3.0.0,<4.0.0)
Requires-Dist: libsasscompiler (>=0.1.5,<0.2.0)
Requires-Dist: pypugjs (>=5.9.8,<6.0.0)
